alphafilter.py
alpha_filter-0.9.dist-info/METADATA
alpha_filter-0.9.dist-info/WHEEL
alpha_filter-0.9.dist-info/top_level.txt
alpha_filter-0.9.dist-info/RECORD
