Metadata-Version: 2.1
Name: alpha-filter
Version: 0.9
Summary: differential filter
Requires-Python: >=3.8
